archive_pmakeup_plugin/ArchivePMakeupPlugin.py
archive_pmakeup_plugin/__init__.py
archive_pmakeup_plugin/version.py
archive_pmakeup_plugin-1.0.4.dist-info/METADATA
archive_pmakeup_plugin-1.0.4.dist-info/WHEEL
archive_pmakeup_plugin-1.0.4.dist-info/top_level.txt
archive_pmakeup_plugin-1.0.4.dist-info/RECORD
